f40_toolkit/__init__.py
f40_toolkit/cache/__init__.py
f40_toolkit/cache/errors.py
f40_toolkit/cache/factory.py
f40_toolkit/cache/interfaces.py
f40_toolkit/cache/keys.py
f40_toolkit/cache/manager.py
f40_toolkit/cache/observability.py
f40_toolkit/cache/serializers.py
f40_toolkit/cache/utils.py
f40_toolkit/cache/backends/file_backend.py
f40_toolkit/cache/backends/memory_backend.py
f40_toolkit/cache/backends/redis_backend.py
f40_toolkit/common/__init__.py
f40_toolkit/common/dicts.py
f40_toolkit/common/env.py
f40_toolkit/common/fs.py
f40_toolkit/common/logging.py
f40_toolkit/common/redaction.py
f40_toolkit/config/__init__.py
f40_toolkit/config/loader.py
f40_toolkit/logging/__init__.py
f40_toolkit/logging/config.py
f40_toolkit/logging/core.py
f40_toolkit/logging/session.py
f40_toolkit-0.1.4.dist-info/licenses/LICENSE
f40_toolkit-0.1.4.dist-info/METADATA
f40_toolkit-0.1.4.dist-info/WHEEL
f40_toolkit-0.1.4.dist-info/top_level.txt
f40_toolkit-0.1.4.dist-info/RECORD
