Metadata-Version: 2.4
Name: f40-toolkit
Version: 0.1.4
Summary: Shared config, logging, cache and common tooling for 40F services.
Author-email: 40F Engineering <dev@40-factory.com>
License-Expression: MIT
Project-URL: Source, https://bitbucket.org/40factory/f40-toolkit/src/main/
Project-URL: Documentation, https://bitbucket.org/40factory/f40-toolkit/src/main/docs/
Classifier: Programming Language :: Python :: 3
Classifier: Programming Language :: Python :: 3.12
Classifier: Programming Language :: Python :: 3.13
Classifier: Programming Language :: Python :: 3.14
Classifier: Intended Audience :: Developers
Classifier: Topic :: Software Development :: Libraries
Requires-Python: >=3.12
License-File: LICENSE
Provides-Extra: cache
Provides-Extra: docs
Requires-Dist: mkdocs; extra == "docs"
Requires-Dist: mkdocs-material; extra == "docs"
Requires-Dist: mkdocstrings[python]; extra == "docs"
Requires-Dist: mkdocs-autorefs; extra == "docs"
Provides-Extra: cache-redis
Requires-Dist: redis>=5.0; python_version >= "3.12" and extra == "cache-redis"
Provides-Extra: config
Requires-Dist: pyyaml>=6.0; extra == "config"
Provides-Extra: all
Requires-Dist: redis>=5.0; python_version >= "3.12" and extra == "all"
Requires-Dist: pyyaml>=6.0; extra == "all"
Provides-Extra: dev
Requires-Dist: pytest>=8; extra == "dev"
Requires-Dist: mypy>=1.11; extra == "dev"
Requires-Dist: ruff>=0.6; extra == "dev"
Requires-Dist: build>=1.2; extra == "dev"
Requires-Dist: twine>=5.0; extra == "dev"
Dynamic: license-file
